pytom3d/__init__.py
pytom3d/core.py
pytom3d/scan.py
pytom3d/stats.py
pytom3d/util.py
pytom3d/viewer.py
pytom3d-0.0.0rc6.dist-info/LICENSE
pytom3d-0.0.0rc6.dist-info/METADATA
pytom3d-0.0.0rc6.dist-info/WHEEL
pytom3d-0.0.0rc6.dist-info/top_level.txt
pytom3d-0.0.0rc6.dist-info/RECORD
